SchemeYuyanJianmingJiaocheng/README.md
SchemeYuyanJianmingJiaocheng/__init__.py
SchemeYuyanJianmingJiaocheng/__main__.py
SchemeYuyanJianmingJiaocheng/file.epub
SchemeYuyanJianmingJiaocheng/index.html
SchemeYuyanJianmingJiaocheng/css/__init__.py
SchemeYuyanJianmingJiaocheng/css/annotations.css
SchemeYuyanJianmingJiaocheng/css/main.css
SchemeYuyanJianmingJiaocheng/css/normalize.css
SchemeYuyanJianmingJiaocheng/css/popup.css
SchemeYuyanJianmingJiaocheng/font/__init__.py
SchemeYuyanJianmingJiaocheng/font/fontello.eot
SchemeYuyanJianmingJiaocheng/font/fontello.svg
SchemeYuyanJianmingJiaocheng/font/fontello.ttf
SchemeYuyanJianmingJiaocheng/font/fontello.woff
SchemeYuyanJianmingJiaocheng/img/__init__.py
SchemeYuyanJianmingJiaocheng/img/annotator-glyph-sprite.png
SchemeYuyanJianmingJiaocheng/img/annotator-icon-sprite.png
SchemeYuyanJianmingJiaocheng/img/apple-touch-icon.png
SchemeYuyanJianmingJiaocheng/img/cancelfullscreen.png
SchemeYuyanJianmingJiaocheng/img/close.png
SchemeYuyanJianmingJiaocheng/img/fullscreen.png
SchemeYuyanJianmingJiaocheng/img/loader.gif
SchemeYuyanJianmingJiaocheng/img/menu-icon.png
SchemeYuyanJianmingJiaocheng/img/save.png
SchemeYuyanJianmingJiaocheng/img/saved.png
SchemeYuyanJianmingJiaocheng/img/settings-s.png
SchemeYuyanJianmingJiaocheng/img/settings.png
SchemeYuyanJianmingJiaocheng/img/star.png
SchemeYuyanJianmingJiaocheng/js/__init__.py
SchemeYuyanJianmingJiaocheng/js/epub.js
SchemeYuyanJianmingJiaocheng/js/epub.min.js
SchemeYuyanJianmingJiaocheng/js/epub.min.map
SchemeYuyanJianmingJiaocheng/js/hooks.min.js
SchemeYuyanJianmingJiaocheng/js/hooks.min.map
SchemeYuyanJianmingJiaocheng/js/reader.js
SchemeYuyanJianmingJiaocheng/js/reader.js.map
SchemeYuyanJianmingJiaocheng/js/reader.min.js
SchemeYuyanJianmingJiaocheng/js/reader.min.map
SchemeYuyanJianmingJiaocheng/js/hooks/__init__.py
SchemeYuyanJianmingJiaocheng/js/hooks/extensions/__init__.py
SchemeYuyanJianmingJiaocheng/js/hooks/extensions/highlight.js
scheme_yuyan_jianming_jiaocheng-2024.3.1.0.dist-info/METADATA
scheme_yuyan_jianming_jiaocheng-2024.3.1.0.dist-info/WHEEL
scheme_yuyan_jianming_jiaocheng-2024.3.1.0.dist-info/entry_points.txt
scheme_yuyan_jianming_jiaocheng-2024.3.1.0.dist-info/top_level.txt
scheme_yuyan_jianming_jiaocheng-2024.3.1.0.dist-info/RECORD
